setup.cfg
setup.py
tankbuster/__init__.py
tankbuster.egg-info/PKG-INFO
tankbuster.egg-info/SOURCES.txt
tankbuster.egg-info/dependency_links.txt
tankbuster.egg-info/requires.txt
tankbuster.egg-info/top_level.txt
tankbuster/cnn/__init__.py
tankbuster/cnn/nets.py
tankbuster/engine/__init__.py
tankbuster/engine/detect.py