Metadata-Version: 1.1
Name: tankbuster
Version: 0.3.1
Summary: A neural network trained to detect Soviet/Russian military vehicles in photographs
Home-page: https://github.com/thiippal/tankbuster
Author: Tuomo Hiippala
Author-email: tuomo.hiippala@iki.fi
License: MIT
Download-URL: https://github.com/thiippal/tankbuster/archive/0.3.1.tar.gz
Keywords: osint,computer vision,object recognition,deep learning,neural network
Platform: UNKNOWN
Classifier: Programming Language :: Python :: 2.7
